<odoo>
    <data>
        <template id="report_expense_month">
            <t t-call="web.html_container">
                <t t-foreach="docs" t-as="o">
                    <t t-call="web.external_layout">
                        <div class="page">
                            <div style="margin:0 auto;width:300px;height:40px; text-align:center;">
                                <p style="font-size:20px; font-weight:bold;">月度差旅及普通招待报销单</p>
                                <p t-field="o.name"/>
                            </div>
                            <div style="width:600px; height:40px; font-size:16px;">
                                <div style="width:290px; height:40px; float:left;">员工: <span t-field="o.seller_id.complete_name"/></div>
                                <div style="width:290px; height:40px; margin-left:8px; float:left;">单据日期: <span t-field="o.bill_date"/></div>
                            </div>

                            <t t-if="o.travel_application_ids">
                                <div><h4>差旅报销</h4></div>
                                <table style="border-collapse:collapse; border-spacing:0; border-left:1px solid #888; border-top:1px solid #888;">
                                    <thead>
                                        <tr>
                                            <th style="font-weight:bold;background:#696969; height:24px; line-height:24px;border-right:1px solid #888;border-bottom:1px solid #888;padding:5px 15px;">单据号</th>
                                            <th style="font-weight:bold;background:#696969; height:24px; line-height:24px;border-right:1px solid #888;border-bottom:1px solid #888;padding:5px 15px;">申请人</th>
                                            <th style="font-weight:bold;background:#696969; height:24px; line-height:24px;border-right:1px solid #888;border-bottom:1px solid #888;padding:5px 15px;">申请日期</th>
                                            <th style="font-weight:bold;background:#696969; height:24px; line-height:24px;border-right:1px solid #888;border-bottom:1px solid #888;padding:5px 15px;">部门</th>
                                            <th style="font-weight:bold;background:#696969; height:24px; line-height:24px;border-right:1px solid #888;border-bottom:1px solid #888;padding:5px 15px;">目的地</th>
                                            <th style="font-weight:bold;background:#696969; height:24px; line-height:24px;border-right:1px solid #888;border-bottom:1px solid #888;padding:5px 15px;">交通费合计</th>
                                            <th style="font-weight:bold;background:#696969; height:24px; line-height:24px;border-right:1px solid #888;border-bottom:1px solid #888;padding:5px 15px;">伙食费合计</th>
                                            <th style="font-weight:bold;background:#696969; height:24px; line-height:24px;border-right:1px solid #888;border-bottom:1px solid #888;padding:5px 15px;">住宿费合计</th>
                                            <th style="font-weight:bold;background:#696969; height:24px; line-height:24px;border-right:1px solid #888;border-bottom:1px solid #888;padding:5px 15px;">市内交通费合计</th>
                                            <th style="font-weight:bold;background:#696969; height:24px; line-height:24px;border-right:1px solid #888;border-bottom:1px solid #888;padding:5px 15px;">合计</th>
                                            <th style="font-weight:bold;background:#696969; height:24px; line-height:24px;border-right:1px solid #888;border-bottom:1px solid #888;padding:5px 15px;">审核金额</th>
                                        </tr>
                                    </thead>
                                    <tbody>
                                        <t t-foreach="o.travel_application_ids" t-as="travel">
                                            <tr style="background-color:#DCDCDC; ">
                                                <td style="border-right:1px solid #888;border-bottom:1px solid #888;padding:5px 15px; ">
                                                    <span t-field="travel.name"/>
                                                </td>
                                                <td style="border-right:1px solid #888;border-bottom:1px solid #888;padding:5px 15px; width:100px;">
                                                    <span t-field="travel.applicant_id"/>
                                                </td>
                                                <td style="border-right:1px solid #888;border-bottom:1px solid #888;padding:5px 15px;">
                                                    <span t-field="travel.applicant_date"/></td>
                                                <td style="border-right:1px solid #888;border-bottom:1px solid #888;padding:5px 15px;">
                                                    <span t-field="travel.applicant_department_id"/>
                                                </td>
                                                <td style="border-right:1px solid #888;border-bottom:1px solid #888;padding:5px 15px;">
                                                    <span t-field="travel.destination_city"/>
                                                </td>
                                                <td style="border-right:1px solid #888;border-bottom:1px solid #888;padding:5px 15px;">
                                                    <span t-field="travel.car_total_cost"/>
                                                </td>
                                                <td style="border-right:1px solid #888;border-bottom:1px solid #888;padding:5px 15px;">
                                                    <span t-field="travel.meal_total_cost"/>
                                                </td>
                                                <td style="border-right:1px solid #888;border-bottom:1px solid #888;padding:5px 15px;">
                                                    <span t-field="travel.hotel_total_cost"/>
                                                </td>
                                                <td style="border-right:1px solid #888;border-bottom:1px solid #888;padding:5px 15px;">
                                                    <span t-field="travel.city_car_total_cost"/>
                                                </td>
                                                <td style="border-right:1px solid #888;border-bottom:1px solid #888;padding:5px 15px;">
                                                    <span t-field="travel.total_cost"/>
                                                </td>
                                                <td style="border-right:1px solid #888;border-bottom:1px solid #888;padding:5px 15px;">
                                                    <span t-field="travel.audit_amount"/>
                                                </td>
                                            </tr>
                                            <t t-if="travel.travel_detail_ids">
                                                <!--<tr>-->
                                                    <!--<table style="border-collapse:collapse; border-spacing:0; border-left:1px solid #888; border-top:1px solid #888;">-->
                                                        <!--<thead>-->
                                                            <tr style="font-size:14px;">
                                                                <th width="10%" style="font-weight:bold;background:#ccc; height:24px; line-height:24px;border-right:1px solid #888;border-bottom:1px solid #888;padding:5px 15px;"></th>
                                                                <th width="12%" style="font-weight:bold;background:#ccc; height:24px; line-height:24px;border-right:1px solid #888;border-bottom:1px solid #888;padding:5px 15px;">开始日期</th>
                                                                <th width="12%" style="font-weight:bold;background:#ccc; height:24px; line-height:24px;border-right:1px solid #888;border-bottom:1px solid #888;padding:5px 15px;">结束日期</th>
                                                                <th width="10%" style="font-weight:bold;background:#ccc; height:24px; line-height:24px;border-right:1px solid #888;border-bottom:1px solid #888;padding:5px 15px;">出发地</th>
                                                                <th width="10%" style="font-weight:bold;background:#ccc; height:24px; line-height:24px;border-right:1px solid #888;border-bottom:1px solid #888;padding:5px 15px;">到达城市</th>
                                                                <th width="8%" style="font-weight:bold;background:#ccc; height:24px; line-height:24px;border-right:1px solid #888;border-bottom:1px solid #888;padding:5px 15px;">交通费</th>
                                                                <th width="8%" style="font-weight:bold;background:#ccc; height:24px; line-height:24px;border-right:1px solid #888;border-bottom:1px solid #888;padding:5px 15px;">伙食费</th>
                                                                <th width="8%" style="font-weight:bold;background:#ccc; height:24px; line-height:24px;border-right:1px solid #888;border-bottom:1px solid #888;padding:5px 15px;">住宿费</th>
                                                                <th width="8%" style="font-weight:bold;background:#ccc; height:24px; line-height:24px;border-right:1px solid #888;border-bottom:1px solid #888;padding:5px 15px;">市内交通</th>
                                                                <th width="6%" style="font-weight:bold;background:#ccc; height:24px; line-height:24px;border-right:1px solid #888;border-bottom:1px solid #888;padding:5px 15px;">合计</th>
                                                                <th width="8%" style="font-weight:bold;background:#ccc; height:24px; line-height:24px;border-right:1px solid #888;border-bottom:1px solid #888;padding:5px 15px;"></th>
                                                            </tr>
                                                        <!--</thead>-->
                                                        <!--<tbody>-->
                                                            <!---->
                                                        <!--</tbody>-->
                                                    <!--</table>-->
                                                    <tr t-foreach="travel.travel_detail_ids" t-as="detail" style="font-size:14px;">
                                                        <td style="border-right:1px solid #888;border-bottom:1px solid #888;padding:5px 15px;">

                                                        </td>
                                                        <td style="border-right:1px solid #888;border-bottom:1px solid #888;padding:5px 15px;">
                                                                    <span t-field="detail.start_date"/>
                                                                </td>
                                                                <td style="border-right:1px solid #888;border-bottom:1px solid #888;padding:5px 15px;">
                                                                    <span t-field="detail.end_date"/>
                                                                </td>
                                                                <td style="border-right:1px solid #888;border-bottom:1px solid #888;padding:5px 15px;">
                                                                    <span t-field="detail.from_city"/>
                                                                </td>
                                                                <td style="border-right:1px solid #888;border-bottom:1px solid #888;padding:5px 15px;">
                                                                    <span t-field="detail.to_city"/>
                                                                </td>
                                                                <td style="border-right:1px solid #888;border-bottom:1px solid #888;padding:5px 15px;">
                                                                    <span t-field="detail.car_cost"/>
                                                                </td>
                                                                <td style="border-right:1px solid #888;border-bottom:1px solid #888;padding:5px 15px;">
                                                                    <span t-field="detail.meal_cost"/>
                                                                </td>
                                                                <td style="border-right:1px solid #888;border-bottom:1px solid #888;padding:5px 15px;">
                                                                    <span t-field="detail.hotel_cost"/>
                                                                </td>
                                                                <td style="border-right:1px solid #888;border-bottom:1px solid #888;padding:5px 15px;">
                                                                    <span t-field="detail.city_car_cost"/>
                                                                </td>
                                                                <td style="border-right:1px solid #888;border-bottom:1px solid #888;padding:5px 15px;">
                                                                    <span t-field="detail.total_cost"/>
                                                                </td>
                                                                <td style="border-right:1px solid #888;border-bottom:1px solid #888;padding:5px 15px;">

                                                                </td>
                                                            </tr>
                                                <!--</tr>-->
                                            </t>
                                        </t>
                                        <tr>
                                            <td colspan="5" style="border-right:1px solid #888;border-bottom:1px solid #888;padding:5px 15px;">

                                            </td>

                                            <td style="border-right:1px solid #888;border-bottom:1px solid #888;padding:5px 15px;">
                                                <span t-field="o.meal_total_cost"/>
                                            </td>
                                            <td style="border-right:1px solid #888;border-bottom:1px solid #888;padding:5px 15px;">
                                                <span t-field="o.hotel_total_cost"/>
                                            </td>
                                            <td style="border-right:1px solid #888;border-bottom:1px solid #888;padding:5px 15px;">
                                                <span t-field="o.car_total_cost"/>
                                            </td>
                                            <td style="border-right:1px solid #888;border-bottom:1px solid #888;padding:5px 15px;">
                                                <span t-field="o.city_car_total_cost"/>
                                            </td>
                                            <td style="border-right:1px solid #888;border-bottom:1px solid #888;padding:5px 15px;">
                                                <span t-field="o.total_travel_applicant_amount"/>
                                            </td>
                                            <td style="border-right:1px solid #888;border-bottom:1px solid #888;padding:5px 15px;">
                                                <span t-field="o.total_travel_audit_amount"/>
                                            </td>
                                        </tr>
                                    </tbody>
                                </table>
                            </t>

                            <t t-if="o.ordinary_application_ids">
                                <div style="padding-top:10px;"><h4>普通招待</h4></div>
                                <table style="border-collapse:collapse; border-spacing:0; border-left:1px solid #888; border-top:1px solid #888;">
                                    <thead>
                                        <tr>
                                            <th style="font-weight:bold;background:#696969; height:24px; line-height:24px;border-right:1px solid #888;border-bottom:1px solid #888;padding:5px 15px;">单据号</th>
                                            <th style="font-weight:bold;background:#696969; height:24px; line-height:24px;border-right:1px solid #888;border-bottom:1px solid #888;padding:5px 15px;">申请人</th>
                                            <th style="font-weight:bold;background:#696969; height:24px; line-height:24px;border-right:1px solid #888;border-bottom:1px solid #888;padding:5px 15px;">申请日期</th>
                                            <th style="font-weight:bold;background:#696969; height:24px; line-height:24px;border-right:1px solid #888;border-bottom:1px solid #888;padding:5px 15px;">部门</th>
                                            <th style="font-weight:bold;background:#696969; height:24px; line-height:24px;border-right:1px solid #888;border-bottom:1px solid #888;padding:5px 15px;">招待日期</th>
                                            <th style="font-weight:bold;background:#696969; height:24px; line-height:24px;border-right:1px solid #888;border-bottom:1px solid #888;padding:5px 15px;">申请金额</th>
                                            <th style="font-weight:bold;background:#696969; height:24px; line-height:24px;border-right:1px solid #888;border-bottom:1px solid #888;padding:5px 15px;">审核金额</th>
                                        </tr>
                                    </thead>
                                    <tbody>
                                        <tr t-foreach="o.ordinary_application_ids" t-as="ordinary">
                                            <td style="border-right:1px solid #888;border-bottom:1px solid #888;padding:5px 15px;">
                                                <span t-field="ordinary.name"/>
                                            </td>
                                            <td style="border-right:1px solid #888;border-bottom:1px solid #888;padding:5px 15px; width:100px;">
                                                <span t-field="ordinary.applicant_id"/>
                                            </td>
                                            <td style="border-right:1px solid #888;border-bottom:1px solid #888;padding:5px 15px;">
                                                <span t-field="ordinary.applicant_date"/></td>

                                            <td style="border-right:1px solid #888;border-bottom:1px solid #888;padding:5px 15px;">
                                                <span t-field="ordinary.applicant_department_id"/>
                                            </td>
                                            <td style="border-right:1px solid #888;border-bottom:1px solid #888;padding:5px 15px;">
                                                <span t-field="ordinary.happen_date"/>
                                            </td>
                                            <td style="border-right:1px solid #888;border-bottom:1px solid #888;padding:5px 15px;">
                                                <span t-field="ordinary.applicant_amount"/>
                                            </td>
                                            <td style="border-right:1px solid #888;border-bottom:1px solid #888;padding:5px 15px;">
                                                <span t-field="ordinary.audit_amount"/>
                                            </td>
                                        </tr>
                                        <tr>
                                            <td colspan="5" style="border-right:1px solid #888;border-bottom:1px solid #888;padding:5px 15px;">

                                            </td>

                                            <td style="border-right:1px solid #888;border-bottom:1px solid #888;padding:5px 15px;">
                                                <span t-field="o.total_ordinary_applicant_amount"/>
                                            </td>
                                            <td style="border-right:1px solid #888;border-bottom:1px solid #888;padding:5px 15px;">
                                                <span t-field="o.total_ordinary_audit_amount"/>
                                            </td>
                                        </tr>
                                    </tbody>
                                </table>
                            </t>

                        </div>
                    </t>
                </t>
            </t>
        </template>

        <template id="report_expense_month_travel">
            <t t-call="web.html_container">
                <t t-foreach="docs" t-as="o">
                    <t t-if="o.travel_application_ids">
                        <t t-foreach="o.travel_application_ids" t-as="travel">
                            <t t-call="web.external_layout">
                                <div class="page">
                                    <div class="row">
                                        <div style="margin:0 auto;width:300px;height:80px; font-size:24px; font-weight:bold; text-align:center;">
                                            差旅报销单<p t-field="travel.name"/>
                                        </div>
                                        <div style="margin:0 auto;width:80%;height:auto; font-size:16px; ">
                                            <table style="width:100%;">
                                                <tr style="height: 30px;">
                                                    <td width="10%">申请人</td>
                                                    <td width="40%"><span t-field="travel.applicant_id" /></td>
                                                    <td width="10%">申请日期</td>
                                                    <td width="40%"><span t-field="travel.applicant_date" /></td>
                                                </tr>
                                                <tr style="height: 30px;">
                                                    <td>部门</td>
                                                    <td><span t-field="travel.applicant_department_id" /></td>
                                                    <td>目的地</td>
                                                    <td><span t-field="travel.destination_city" /></td>
                                                </tr>
                                                <tr style="height: 30px;">
                                                    <td>事由</td>
                                                    <td><span t-field="travel.cause" /></td>
                                                    <td>备注</td>
                                                    <td><span t-field="travel.reimbursement_remark" /></td>
                                                </tr>
                                            </table>
                                        </div>
                                        <div style="margin:0 auto;width:100%;height:auto; font-size:16px; ">
                                            <t t-if="travel.travel_detail_ids">
                                                <div style="margin:0 auto;width:100%;height:auto; font-size:22px; font-weight:bold; padding-bottom:10px;">
                                                    差旅明细
                                                </div>
                                                <table style="border-collapse:collapse; border-spacing:0; border-left:1px solid #888; border-top:1px solid #888;">
                                                    <thead>
                                                        <tr style="font-size:16px;">
                                                            <th width="12%" style="font-weight:bold;background:#ccc; height:24px; line-height:24px;border-right:1px solid #888;border-bottom:1px solid #888;padding:5px 15px;">开始日期</th>
                                                            <th width="12%" style="font-weight:bold;background:#ccc; height:24px; line-height:24px;border-right:1px solid #888;border-bottom:1px solid #888;padding:5px 15px;">结束日期</th>
                                                            <th width="10%" style="font-weight:bold;background:#ccc; height:24px; line-height:24px;border-right:1px solid #888;border-bottom:1px solid #888;padding:5px 15px;">出发地</th>
                                                            <th width="10%" style="font-weight:bold;background:#ccc; height:24px; line-height:24px;border-right:1px solid #888;border-bottom:1px solid #888;padding:5px 15px;">到达城市</th>
                                                            <th width="8%" style="font-weight:bold;background:#ccc; height:24px; line-height:24px;border-right:1px solid #888;border-bottom:1px solid #888;padding:5px 15px;">交通费</th>
                                                            <th width="8%" style="font-weight:bold;background:#ccc; height:24px; line-height:24px;border-right:1px solid #888;border-bottom:1px solid #888;padding:5px 15px;">伙食费</th>
                                                            <th width="8%" style="font-weight:bold;background:#ccc; height:24px; line-height:24px;border-right:1px solid #888;border-bottom:1px solid #888;padding:5px 15px;">住宿费</th>
                                                            <th width="8%" style="font-weight:bold;background:#ccc; height:24px; line-height:24px;border-right:1px solid #888;border-bottom:1px solid #888;padding:5px 15px;">市内交通</th>
                                                            <th width="6%" style="font-weight:bold;background:#ccc; height:24px; line-height:24px;border-right:1px solid #888;border-bottom:1px solid #888;padding:5px 15px;">合计</th>
                                                        </tr>
                                                    </thead>
                                                    <tbody>
                                                        <tr t-foreach="travel.travel_detail_ids" t-as="detail" style="font-size:16px;">
                                                            <td style="border-right:1px solid #888;border-bottom:1px solid #888;padding:5px 15px;">
                                                                <span t-field="detail.start_date"/>
                                                            </td>
                                                            <td style="border-right:1px solid #888;border-bottom:1px solid #888;padding:5px 15px;">
                                                                <span t-field="detail.end_date"/>
                                                            </td>
                                                            <td style="border-right:1px solid #888;border-bottom:1px solid #888;padding:5px 15px;">
                                                                <span t-field="detail.from_city"/>
                                                            </td>
                                                            <td style="border-right:1px solid #888;border-bottom:1px solid #888;padding:5px 15px;">
                                                                <span t-field="detail.to_city"/>
                                                            </td>
                                                            <td style="border-right:1px solid #888;border-bottom:1px solid #888;padding:5px 15px;">
                                                                <span t-field="detail.car_cost"/>
                                                            </td>
                                                            <td style="border-right:1px solid #888;border-bottom:1px solid #888;padding:5px 15px;">
                                                                <span t-field="detail.meal_cost"/>
                                                            </td>
                                                            <td style="border-right:1px solid #888;border-bottom:1px solid #888;padding:5px 15px;">
                                                                <span t-field="detail.hotel_cost"/>
                                                            </td>
                                                            <td style="border-right:1px solid #888;border-bottom:1px solid #888;padding:5px 15px;">
                                                                <span t-field="detail.city_car_cost"/>
                                                            </td>
                                                            <td style="border-right:1px solid #888;border-bottom:1px solid #888;padding:5px 15px;">
                                                                <span t-field="detail.total_cost"/>
                                                            </td>
                                                        </tr>
                                                        <tr style="font-size:16px;">
                                                            <td colspan="4" style="border-right:1px solid #888;border-bottom:1px solid #888;padding:5px 15px;">

                                                            </td>
                                                            <td style="border-right:1px solid #888;border-bottom:1px solid #888;padding:5px 15px;">
                                                                <span t-field="travel.car_total_cost"/>
                                                            </td>
                                                            <td style="border-right:1px solid #888;border-bottom:1px solid #888;padding:5px 15px;">
                                                                <span t-field="travel.meal_total_cost"/>
                                                            </td>
                                                            <td style="border-right:1px solid #888;border-bottom:1px solid #888;padding:5px 15px;">
                                                                <span t-field="travel.hotel_total_cost"/>
                                                            </td>
                                                            <td style="border-right:1px solid #888;border-bottom:1px solid #888;padding:5px 15px;">
                                                                <span t-field="travel.city_car_total_cost"/>
                                                            </td>
                                                            <td style="border-right:1px solid #888;border-bottom:1px solid #888;padding:5px 15px;">
                                                                <span t-field="travel.total_cost"/>
                                                            </td>
                                                        </tr>
                                                    </tbody>
                                                </table>
                                            </t>
                                        </div>
                                        <div style="margin:0 auto;width:100%;height:auto; font-size:22px; font-weight:bold; padding-top:20px; padding-bottom:10px;">
                                            财务审核信息
                                        </div>
                                        <div style="margin:0 auto;width:80%;height:auto; font-size:16px; ">
                                            <table style="width:100%;">
                                                <tr style="height: 30px;">
                                                    <td width="10%">核减金额</td>
                                                    <td width="40%"><span t-field="travel.audit_cut_amount" /></td>
                                                    <td width="10%">审核金额</td>
                                                    <td width="40%"><span t-field="travel.audit_amount" /></td>
                                                </tr>
                                                <tr>
                                                    <td>审核备注</td>
                                                    <td colspan="3">
                                                        <span t-field="travel.audit_remark" />
                                                    </td>
                                                </tr>
                                            </table>
                                        </div>
                                        <div style="margin:0 auto;width:100%;height:auto; font-size:22px; font-weight:bold; padding-top:20px; padding-bottom:10px;">
                                            报销信息
                                        </div>
                                        <div style="margin:0 auto;width:80%;height:auto; font-size:16px; ">
                                            <table style="width:100%;">
                                                <tr style="height: 30px;">
                                                    <td width="10%">报销人员</td>
                                                    <td width="40%"><span t-field="travel.reimbursement_person_id" /></td>
                                                    <td width="10%">支付方式</td>
                                                    <td width="40%"><span t-field="travel.reimbursement_payment_method" /></td>
                                                </tr>
                                                <tr style="height: 30px;">
                                                    <td>开户行</td>
                                                    <td><span t-field="travel.bank_name" /></td>
                                                    <td>银行账户</td>
                                                    <td><span t-field="travel.bank_account" /></td>
                                                </tr>
                                            </table>
                                        </div>

                                    </div>
                                </div>
                            </t>
                        </t>

                    </t>
                </t>
            </t>
        </template>

        <template id="report_expense_month_ordinary">
            <t t-call="web.html_container">
                <t t-foreach="docs" t-as="o">
                    <t t-if="o.travel_application_ids">
                        <t t-foreach="o.ordinary_application_ids" t-as="ordinary">
                            <t t-call="web.external_layout">
                                <div class="page">
                                    <div class="row">
                                        <div style="margin:0 auto;width:300px;height:80px; font-size:24px; font-weight:bold; text-align:center;">
                                            普通招待报销单<p t-field="ordinary.name"/>
                                        </div>
                                        <div style="margin:0 auto;width:80%;height:auto; font-size:16px; ">
                                            <table style="width:100%;">
                                                <tr style="height: 30px;">
                                                    <td width="10%">申请人</td>
                                                    <td width="40%"><span t-field="ordinary.applicant_id" /></td>
                                                    <td width="10%">申请日期</td>
                                                    <td width="40%"><span t-field="ordinary.applicant_date" /></td>
                                                </tr>
                                                <tr style="height: 30px;">
                                                    <td>部门</td>
                                                    <td><span t-field="ordinary.applicant_department_id" /></td>
                                                    <td>招待日期</td>
                                                    <td><span t-field="ordinary.happen_date" /></td>
                                                </tr>
                                                <tr style="height: 30px;">
                                                    <td>事由</td>
                                                    <td><span t-field="ordinary.cause" /></td>
                                                    <td>备注</td>
                                                    <td><span t-field="ordinary.reimbursement_remark" /></td>
                                                </tr>
                                                <tr style="height: 30px;">
                                                    <td>金额</td>
                                                    <td><span t-field="ordinary.applicant_amount" /></td>
                                                    <td></td>
                                                    <td></td>
                                                </tr>
                                            </table>
                                        </div>

                                        <div style="margin:0 auto;width:100%;height:auto; font-size:22px; font-weight:bold; padding-top:20px; padding-bottom:10px;">
                                            财务审核信息
                                        </div>
                                        <div style="margin:0 auto;width:80%;height:auto; font-size:16px; ">
                                            <table style="width:100%;">
                                                <tr style="height: 30px;">
                                                    <td width="10%">审核金额</td>
                                                    <td width="40%"><span t-field="ordinary.audit_amount" /></td>
                                                    <td width="10%"></td>
                                                    <td width="40%"></td>
                                                </tr>
                                            </table>
                                        </div>
                                        <div style="margin:0 auto;width:100%;height:auto; font-size:22px; font-weight:bold; padding-top:20px; padding-bottom:10px;">
                                            报销信息
                                        </div>
                                        <div style="margin:0 auto;width:80%;height:auto; font-size:16px; ">
                                            <table style="width:100%;">
                                                <tr style="height: 30px;">
                                                    <td width="10%">报销人员</td>
                                                    <td width="40%"><span t-field="ordinary.reimbursement_person_id" /></td>
                                                    <td width="10%">支付方式</td>
                                                    <td width="40%"><span t-field="ordinary.reimbursement_payment_method" /></td>
                                                </tr>
                                                <tr style="height: 30px;">
                                                    <td>开户行</td>
                                                    <td><span t-field="ordinary.bank_name" /></td>
                                                    <td>银行账户</td>
                                                    <td><span t-field="ordinary.bank_account" /></td>
                                                </tr>
                                            </table>
                                        </div>

                                    </div>
                                </div>
                            </t>
                        </t>

                    </t>
                </t>
            </t>
        </template>
    </data>
</odoo>